{"keys": ["21220", "21164", "21497", "16918", "17299", "16869", "21501", "21166", "21154", "21167", "21159", "21155", "21157", "21515", "13378", "13173", "17294"], "data": {"21220": {"zone": "5b"}, "21515": {"zone": "5b"}, "16918": {"zone": "6a"}, "16869": {"zone": "6a"}, "21497": {"zone": "5b"}, "21159": {"zone": "5b"}, "21166": {"zone": "5b"}, "21501": {"zone": "5b"}, "17299": {"zone": "6a"}, "13378": {"zone": "6b"}, "17294": {"zone": "6a"}, "21157": {"zone": "5b"}, "13173": {"zone": "6b"}, "21155": {"zone": "5b"}, "21167": {"zone": "5b"}, "21154": {"zone": "5b"}, "21164": {"zone": "5b"}}, "grid": ["                                           !!!!!!!!!!!!!!!!!!!!!", "                                           !!!!!!!!!!!!!!!!!!!!!", "                                          !!!!!!!!!!!!!!!!!!!!!!", "                                         !!!!!!!!!!!!!!!!!!!!!!!", "                                        !!!!!!!!!!!!!!!!!!!!!!!!", "                                        !!!!!!!!!!!!!!!!!!!!!!!!", "                                        !!!!!!!!!!!!!!!!!!!!!!!!", "                                       !!!!!!!!!!!!!!!!!!!!!!!!!", "                                       !!!!!!!!!!!!!!!!!!!!!!!!!", "                                       !!!!!!!!!!!!!!!!!!!!!!!!!", "                                      !!!!!!!!!!!!!!!!!!!!!!!!!!", "                    #####         !!!!!!!!!!!!!!!!!!!!!!!!!!!!!!", "##########################       !!!!!!!!!!!!!!!!!!!!!!!!!!!!!!!", "############################     !!!!!!!!!!!!!!!!!!!!!!!!!!!!!!!", "############################     !!!!!!!!!!!!!!!!!!!!!!!!!!!!!!!", "#############################    !!!!!!!!!!!!!!!!!!!!!!!!!!!!!!!", "##############################   !!!!!!!!!!!!!!!!!!!!!!!!!!!!!!!", "##############################$  !!!!!!!!!!!!!!!!!!!!!!!!!!!!!!!", "#############################%%%!!!!!!!!!!!!!!!!!!!!!!!!!!!!!!!!", "#############################%%&!!!!!!!!!!!!!!!!!!!!!!!!!!!!!!!!", "#############################%%&!!!!!!!!!!!!!!!!!!!!!!!!!!!!!!!!", "#############################%%&!!!!!!!!!!!!!!!!!!!!!!!!!!!!!!!!", "##########################%##%&&!!!!!!!!!!!!!!!!!!!!!!!!!!!!!!!!", "#########################%%%%%&&!!!!!!!!!!!!!!!!!!!!!!!!!!!!!!!!", "###########################%%%&&&&&!!!!!!!!!!!!!!!!!!!!!!!!!!!!!", "######################%##%%%%%&&&&&!!!!!!!!!!!!!!!!!!!!!!!!!!!!!", "########################%%%%%%&&&&!!!!!!!!!!!!!!!!!!!!!!!!!!!!!!", "########################%%%%%%&&&&&!&!!!!!!!!!!!!!!!!!&&!!!!!!!!", "########################%%%%%%%&&&&&&!!!!!!!!!!!!!!!!&&&!!!!!!!!", "########################%%%%%%%&&&&&&&&!!!!!!!!!!!!!&&&&!!!!!!!!", "#######################%%%%%%%%&&&&&&&&&!!!!!!!!!!!!&&&!!!!!!!!!", "########################%%%%%%%%&&&&&&&&&!!!!!!!!!!!&!!!!!!!!!!!", "########################%%%%%%%%&&&&&&&&&&!!!!!!!!!&&!!!!!!!!!!!", "#####################%%'%%%%%%%%&&&&&&&&!!!!!!!!&!&&&!!!!!!!!!!!", "#####################%%%%%%%%%%%&&&&&&(&!!!!!!!!!&&&&!!!!!&!!!!!", "#####################%%%%%%%%%%%%&&&&&&&!!!!!!!!&&&&&!!!!&&&!!&&", "#####################%%%%%%%%%%%%&&&&&&&&!!!!!!&&&&&&&!&!&&&!!&&", "#%%%#################%%%%%%%%%%%%&&&&&&&&&!!!!!&&&&&&&&&!&&&&!&&", "##%%#################%%%%%%%%%%%%%&&&&&&&!!!!!!!&&&&&&&&!!&&&&&&", "%%%%%%####%##########%%%%%%%%%%%%%%%&&&&&&&!!!!&&&&&&&&&&)&&&&&&", "%%%%%%%%##%%########%%%%%%%%%%%%%%%%&&&&&*!!!!!&&&&&&&&&&&&&&&&&", "%%%%%%%%#%%%%%%%####%%%%%%%%%%%%%%%%%%&&&&!!!!!!+&&&&&&&&,,&&&&&", "%%%%%%%%%%%%%%%%%%%%%%%%%%%%%%%%%%%%%%&&&&&!&&&&&+&&&&&&,,&&&&&&", "%%%%%%%%%%%%%%%%%%%%%%%%%%%%%%%%%%%%%%%%&&&&&&&&&&&&&&&,,&&&&&&&", "%%%%%%%%%%%%%%%%%%%%%%%%%%%%%%%%%%%%%%%%&&&&&&&&&&&&&-&,&&&&&&&&", "%%%%%%%%%%%%%%%%%%%%%%%%%%%%%%%%%.....%%%&&&&&&&&&&&&&,,&&&&&&&&", "%%%%%%%%%%%%%%%%%%%%%%%%%%%%%%%%%.......%%&&&&&&&&&&&&&&&&&&&&&&", "%%%%%%%%%%%%%%%%%%%%%%%%%%%%%%%%%......%%%%&&&&&&&&&&&&&&&&&&&&&", "%%%%%%%%%%%%%%%%%%%%%%%%%%%%%%%%%%.....%%%%%%&&&&&&&&&&&&&&&&&&&", "%%%%%%%%%%%%%%%%%%%%%%%%%%%%%%%%%%.....%%%%%%%&&&&&&&&&&&&&&&&&&", "%%%%%%%%%%%%%%%%%%%%%%%%%%%%%%%%%%.....%%%%%%%%&&&&&&&&&&&&&&&&&", "%%%%%%%%%%%%%%%%%%%%%%%%%%%%%%%%%%%....%%%%%%%%%&&&&&&&&&&&&&&&&", "%%%%%%%%%%%%%%%%%%%%%%%%%%%%%%%%%%%%%%%%%%%%%%%%&&&&&&&&&&&&&&&&", "%%%%%%%%%%%%%%%%%%%%%%%%%%%%%%%%%%%%%%%%%%%%%%%%&&&&&&&&&&&&&&&&", "%%%%%%%%%%%%%%%%%%%%%%%%%%%%%%%%%%%%%%%%%%%%%%%%&&&&&&&&&&&&&&&&", "%%%%%%%%%%%%%%%%%%%%%%%%%%%%%%%%%%%%%%%%%%%%%%%%%&&&&&&&&&&&&&&&", "%%%%%%%%%%%%%%%%%%%%%%%%%%%%%%%%%%%%%%%%%%%%%%%%%&&&&&&&&&&&&&&&", "%%%%%%%%%%%%%%%%%%%%%%%%%%%%%%%%%%%%%%%%%%%%%%%%&&&&&&&&&&&&&&&&", "%%%%%%%%%%%%%%%%%%%%%%%%%%%%%%%%%%%%%%%%%%%%%%%%%&&&&&&&&&&&&&&&", "%%%%%%%%%%%%%%%%%%%%%%%%%%%%%%%%%%%%%%%%%%%%%%%%%&&&&&&&&&&&&&&&", "%%%%%%%%%%%%%%%%%%%%%%%%%%%%%%%%%%%%%%%%%%%%%%%%%&&&&%%%&&&&&&&&", "%%%%%%%%%%%%%%%%%%%%%%%%%%%%%%%%%%%%%%%%%%%%%%%%%%&&&%%%///&&&&&", "%%%%%%%%%%%%%%%%%%%%%%%%%%%%%%%%%%%%%%%%%%%%%%%%%%%&%%%%////00&&", "%%%%%%%%%%%%%%%%%%%%%%%%%%%%%%%%%%%%%%%%%%%%%%%%%%%%%%%//1////0&"]}