{"keys": ["", "7095", "7171", "12065", "9265", "12064", "15579", "19424", "15595", "23026", "12081", "19427", "19405", "25900", "23042", "19416", "19486", "23014", "23055", "9287", "9274", "19401", "25901", "22998", "15589"], "data": {"9265": {"zone": "7b"}, "23042": {"zone": "5b"}, "7171": {"zone": "8a"}, "19424": {"zone": "6a"}, "15579": {"zone": "6b"}, "7095": {"zone": "8a"}, "9287": {"zone": "7b"}, "22998": {"zone": "5b"}, "25901": {"zone": "5a"}, "25900": {"zone": "5a"}, "19427": {"zone": "6a"}, "19405": {"zone": "6a"}, "15589": {"zone": "6b"}, "19401": {"zone": "6a"}, "23014": {"zone": "5b"}, "19486": {"zone": "6a"}, "9274": {"zone": "7b"}, "23055": {"zone": "5b"}, "12064": {"zone": "7a"}, "12065": {"zone": "7a"}, "15595": {"zone": "6b"}, "23026": {"zone": "5b"}, "12081": {"zone": "7a"}, "19416": {"zone": "6a"}}, "grid": ["                                                                ", "                                                                ", "                                                                ", "                                                                ", "                                                                ", "                                                                ", "                                                                ", "                                                                ", "                                                                ", "                                                                ", "                                                                ", "                                                                ", "                                                                ", "                                                                ", "                                                                ", "                                                                ", "                                                                ", "                                                                ", "                                                                ", "                                                                ", "                                                                ", "                                                                ", "                                                                ", "                                                                ", "                                                                ", "                                                                ", "                                                                ", "                                                                ", "                                                                ", "                                                                ", "                                                                ", "                                                                ", "                                                                ", "                                                                ", "                                                                ", "                                                                ", "                                                                ", "                                                                ", "                                                                ", "                                                                ", "                                                                ", "                                                                ", "                                                                ", "                                                                ", "                                                                ", "                                                                ", "                                                                ", "                                                                ", "                                                                ", "                                                                ", "                                                                ", "                                                                ", "                                                                ", "                                                                ", "                                                                ", "                                                                ", "                                                                ", "                                                                ", "                                                                ", "                                                                ", "                                                                ", "                                                                ", "                !       ###############$%&&&''()*+,,,''--./00123", "                      ##############45#%%%&&'''((6+,,''-78/09123"]}