{"keys": ["5318", "3677", "3676", "3674", "3659", "3648", "3641", "3671", "3633", "3639", "3656", "5375", "5374", "5333", "5331", "5332", "6033", "4487", "6034", "4489", "6038", "6039"], "data": {"3639": {"zone": "8b"}, "3633": {"zone": "8b"}, "5331": {"zone": "8a"}, "5333": {"zone": "8a"}, "5332": {"zone": "8a"}, "3659": {"zone": "8b"}, "3656": {"zone": "8b"}, "3671": {"zone": "8b"}, "3676": {"zone": "8b"}, "3677": {"zone": "8b"}, "3674": {"zone": "8b"}, "5318": {"zone": "8a"}, "5375": {"zone": "8a"}, "5374": {"zone": "8a"}, "4487": {"zone": "8b"}, "3648": {"zone": "8b"}, "3641": {"zone": "8b"}, "6039": {"zone": "8a"}, "6038": {"zone": "8a"}, "6033": {"zone": "8a"}, "4489": {"zone": "8b"}, "6034": {"zone": "8a"}}, "grid": ["                                                                ", "                                                                ", "                                                                ", "                                                                ", "                                                                ", "                                                                ", "                                                         !!!!   ", "                                                            !!! ", "                                                        #  !!   ", "                                                           !    ", "                                                           !    ", "                                                                ", "                                                                ", "                                                                ", "                                                                ", "                                                              $ ", " %%%                                                            ", " %%%                                                            ", "  %%                                                            ", "  %%     &                                                      ", "                                                                ", " %                   '                                    (     ", " %                                                       (     )", "   %                       *                            (((   ))", "                                                        ((   )))", "                                                       ((   ))))", ")                                                       (  )))))", "                                                         )))))))", ")                                                      )))))))))", ")  +                                                 )))))))))))", ")  +                                                  ))))))))) ", ")  +                                                   )))))))))", ") ++                                                  ))))))))))", "  ++                                                 )))))))))))", "   +                                                  ))))))))))", "  +                                                    )))))))))", "                                                      ))))))))))", "                                                       ) )))))))", ")                                                        )))))),", "                                                         )))))  ", "                                                        ))))))- ", "                                                         )))))) ", "                                                        ))))))))", "                                                        ))))))))", "                                                      ) ))))))))", "                                                        ))))))))", "                                                       )))))))))", "                                                        ))))))))", "           .)                                           ))))))))", "     )   ) ))                                           ))))))))", "    )))))))/)0)                                          )))))))", "1112222223233214111111111111111111111111121111111111111122222222", "1122222223333211111111111111111112111112221111111111111522222222", "2222222223323311111111111111111121111121122211111111111122222222", "2222222222222211111111111111111121111111122221111111112222222222", "2222222222222222111111111111111122111111222221111111122222222222", "2222222222222222221111111111111222111112226221111222222222222222", "2222222222222222222211111111112222211112222221122222222222222222", "2222222222222222222211112111222222222222222222222222222222222222", "2222222222222222222222122122222222222222222222222222222222222222", "2222222222222222222222222222222222222222222222222222222222222222", "2222222222222222222222222222222222222222222222222222222222222222", "2222222222222222222222222222222222222222222222222222222222222222", "2222222222222222222222222222222222222222222222222222222222222222"]}