{"keys": ["6726", "8812", "5020", "5018"], "data": {"5018": {"zone": "8b"}, "5020": {"zone": "8b"}, "6726": {"zone": "8a"}, "8812": {"zone": "7b"}}, "grid": ["                !!!                                             ", "               !!!!                                             ", "               !!!!!                                            ", "               !!!!  !                                          ", "               !!!!!!                                           ", "               !!!!!!                                           ", "                !!!!                                            ", "                                                                ", "                                                                ", "                                                                ", "                                                                ", "                                                                ", "                                                                ", "                                                                ", "                                                                ", "                                                                ", "                                                                ", "                                                                ", "                                                                ", "                                                                ", "                                                                ", "                                                                ", "                                                                ", "                                                                ", "                                                                ", "                                                                ", "                                                                ", "                                                                ", "                                                                ", "                                                                ", "                                                                ", "                                                                ", "                                                                ", "                                                                ", "                                                                ", "                                                                ", "                                                                ", "                                                                ", "                                                                ", "                                           #                    ", "                                                                ", "                                                                ", "                                                                ", "                                           $                    ", "                                        $  $$                   ", "                               $        $$$$$$   $$             ", "                               $$$    $$$$$$$$$  $$$$           ", "                               $$$$      $$$$$$ $$$$$$$         ", "                               $$       $$$$$$$$$$$$$$$$        ", "                              $$   $$$   $$$$$$$$$$$$$$$$      $", "                         $$$  $$$$$$$$ $$$$$$$$$$$$$$$$$$$$ $$$$", "                       $$$$$$$$$$$$$$$$$$$$$$$$$$$$$$$$$$$$$$$$$", "                       $$$$$$$$$$$$$$$$$$$$$$$$$$$$$$$$$$$$$$$$$", "                       $$$$$$$$$$$$$$$$$$$$$$$$$$$$$$$$$$$$$$$$$", "                       $$$$$$$$$$$$$$$$$$$$$$$$$$$$$$$$$$$$$$$$$", "                      $$$$$$$$$$$$$$$$$$$$$$$$$$$$$$$$$$$$$$$$$$", "                    $$$$$$$$$$$$$$$$$$$$$$$$$$$$$$$$$$$$$$$$$$$$", "                     $$$$$$$$$$$$$$$$$$$$$$$$$$$$$$$$$$$$$$$$$$$", "                     $$$$$$$$$$$$$$$$$$$$$$$$$$$$$$$$$$$$$$$$$$$", "                     $$$$$$$$$$$$$$$$$$$$$$$$$$$$$$$$$$$$$$$$$$$", "                       $$$$$$$$$$$$$$$$$$$$$$$$$$$$$$$$$$$$$$$$$", "                       $$$$$$$$$$$$$$$$$$$$$$$$$$$$$$$$$$$$$$$$$", "                      $$$$$$$$$$$$$$$$$$$$$$$$$$$$$$$$$$$$$$$$$$", "                       $$$$$$$$$$$$$$$$$$$$$$$$$$$$$$$$$$$$$$$$$"]}